tshap/synthetic.py
tshap/tshap.py
tshap/xutil.py
tshap-0.0.1.dist-info/licenses/LICENSE
tshap-0.0.1.dist-info/METADATA
tshap-0.0.1.dist-info/WHEEL
tshap-0.0.1.dist-info/top_level.txt
tshap-0.0.1.dist-info/RECORD
