Metadata-Version: 2.4
Name: tshap
Version: 0.0.1
Summary: Fast and Exact SHAP for Explaining Time Series Classification and Regression
Author-email: Thach Le Nguyen <lenguyenthach141@gmail.com>
Project-URL: Homepage, https://github.com/mlgig/tshap
Project-URL: Bug Tracker, https://github.com/mlgig/tshap/issues
Requires-Python: >=3.7
License-File: LICENSE
Dynamic: license-file
